higgsdikits/__init__.py
higgsdikits-0.2.dist-info/LICENSE.txt
higgsdikits-0.2.dist-info/METADATA
higgsdikits-0.2.dist-info/WHEEL
higgsdikits-0.2.dist-info/top_level.txt
higgsdikits-0.2.dist-info/RECORD
