Metadata-Version: 2.1
Name: higgsdikits
Version: 0.2
Summary: Some basic ML codes
Home-page: UNKNOWN
Author: 314amruta349043
Author-email: ap8112002@gmail.com
License: UNKNOWN
Platform: UNKNOWN
Classifier: Programming Language :: Python :: 3
Classifier: License :: OSI Approved :: MIT License
Classifier: Operating System :: OS Independent
License-File: LICENSE.txt
